abstractEasyT/__init__.py
abstractEasyT/initialization.py
abstractEasyT/rates.py
abstractEasyT/tick.py
abstractEasyT/timeframe.py
abstractEasyT/trade.py
tests/__init__.py
tests/test_initialization.py
tests/test_rates.py
tests/test_tick.py
tests/test_timeframe.py
tests/test_trade.py
abstractEasyT-0.2.2.dist-info/METADATA
abstractEasyT-0.2.2.dist-info/WHEEL
abstractEasyT-0.2.2.dist-info/top_level.txt
abstractEasyT-0.2.2.dist-info/RECORD
