Metadata-Version: 2.1
Name: abstractEasyT
Version: 0.2.2
Summary: UNKNOWN
Home-page: UNKNOWN
Author: Joao Paulo Euko
License: MIT
Platform: UNKNOWN
